{
  "sido": "대구",
  "district": "대구군위군",
  "specialties": {
    "마취통증의학과": {
      "count": 1,
      "diseases": [
        "신경차단술",
        "경막외 스테로이드",
        "관절강 내 주사"
      ],
      "hospitals": [
        {
          "name": "고려마취통증의학과의원",
          "address": "대구광역시 군위군 군위읍 중앙길 100, (군위읍)",
          "tel": "054-382-0922"
        }
      ]
    },
    "내과": {
      "count": 7,
      "diseases": [
        "급성 심근경색증",
        "협심증",
        "기왕증 기여도 산정",
        "고혈압성 심질환"
      ],
      "hospitals": [
        {
          "name": "박애의원",
          "address": "대구광역시 군위군 효령면 경북대로 2678, 2678",
          "tel": "054-382-0055"
        },
        {
          "name": "서광외과의원",
          "address": "대구광역시 군위군 군위읍 동서1길 17-9, (군위읍)",
          "tel": "054-383-5677"
        },
        {
          "name": "성누가의원",
          "address": "대구광역시 군위군 군위읍 동서길 33, (군위읍)",
          "tel": "054-382-9912"
        },
        {
          "name": "영남한빛의원",
          "address": "대구광역시 군위군 군위읍 중앙길 72, (군위읍)",
          "tel": "054-383-8275"
        },
        {
          "name": "우보큰사랑의원",
          "address": "대구광역시 군위군 우보면 이화길 135, (우보면)",
          "tel": "054-382-8222"
        },
        {
          "name": "의흥동산의원",
          "address": "대구광역시 군위군 의흥면 읍내길 49-10, (의흥면)",
          "tel": "054-382-2730"
        },
        {
          "name": "현대내과의원",
          "address": "대구광역시 군위군 군위읍 중앙길 88, (군위읍)",
          "tel": "054-383-9966"
        }
      ]
    },
    "치과": {
      "count": 3,
      "diseases": [
        "임플란트/치조골 이식술",
        "크라운/브릿지",
        "치주질환"
      ],
      "hospitals": [
        {
          "name": "삼성치과의원",
          "address": "대구광역시 군위군 군위읍 중앙길 89, (군위읍)",
          "tel": "054-383-7528"
        },
        {
          "name": "이광렬치과의원",
          "address": "대구광역시 군위군 군위읍 중앙길 98, (군위읍)",
          "tel": "054-382-1758"
        },
        {
          "name": "이편한치과의원",
          "address": "대구광역시 군위군 군위읍 중앙길 139, (군위읍)",
          "tel": "054-383-7997"
        }
      ]
    },
    "한방내과": {
      "count": 6,
      "diseases": [
        "교통사고 첩약 처방",
        "추나요법",
        "침구 치료"
      ],
      "hospitals": [
        {
          "name": "군위한의원",
          "address": "대구광역시 군위군 군위읍 중앙길 116, (군위읍)",
          "tel": "054-382-0177"
        },
        {
          "name": "권오규한의원",
          "address": "대구광역시 군위군 군위읍 동서1길 20-1, (군위읍)",
          "tel": "053-323-2275"
        },
        {
          "name": "대원한의원",
          "address": "대구광역시 군위군 군위읍 중앙길 91, (군위읍)",
          "tel": "054-382-7582"
        },
        {
          "name": "대흥한의원",
          "address": "대구광역시 군위군 의흥면 읍내길 32-6, (의흥면)",
          "tel": "054-382-7056"
        },
        {
          "name": "석산한의원",
          "address": "대구광역시 군위군 고로면 석산길 233, (삼국유사면)",
          "tel": "054-383-1694"
        },
        {
          "name": "원함한의원",
          "address": "대구광역시 군위군 군위읍 중앙길 126, (군위읍)",
          "tel": "054-382-0305"
        }
      ]
    }
  }
}