{
  "sido": "전북",
  "district": "무주군",
  "specialties": {
    "내과": {
      "count": 7,
      "diseases": [
        "급성 심근경색증",
        "협심증",
        "기왕증 기여도 산정",
        "고혈압성 심질환"
      ],
      "hospitals": [
        {
          "name": "강안의원",
          "address": "전북특별자치도 무주군 무주읍 주계로 72, (무주읍)",
          "tel": "063-324-3900"
        },
        {
          "name": "고려의원",
          "address": "전북특별자치도 무주군 무주읍 단천로 37, 37",
          "tel": ""
        },
        {
          "name": "노금석외과의원",
          "address": "전북특별자치도 무주군 무주읍 주계로 80, 103호 (센트럴 노블리안 아파트)",
          "tel": "063-322-0942"
        },
        {
          "name": "무주한양내과의원",
          "address": "전북특별자치도 무주군 무주읍 한풍루로 351, 351",
          "tel": "063-324-8867"
        },
        {
          "name": "성모외과의원",
          "address": "전북특별자치도 무주군 설천면 무설로 1583, 1583",
          "tel": "063-324-1342"
        },
        {
          "name": "임형래내과의원",
          "address": "전북특별자치도 무주군 무주읍 단천로 99, (무주읍)",
          "tel": "063-322-8275"
        },
        {
          "name": "평화의원",
          "address": "전북특별자치도 무주군 안성면 칠연로 57, (안성면)",
          "tel": "063-323-0203"
        }
      ]
    },
    "신경외과": {
      "count": 1,
      "diseases": [
        "목/허리디스크(추간판탈출증)",
        "척추관협착증",
        "외상성 뇌출혈",
        "경추/요추 염좌",
        "뇌경색"
      ],
      "hospitals": [
        {
          "name": "무주신경외과의원",
          "address": "전북특별자치도 무주군 무주읍 향학로 33-1, 33",
          "tel": "063-324-8275"
        }
      ]
    },
    "안과": {
      "count": 1,
      "diseases": [
        "백내장(다초점 렌즈)",
        "황반변성",
        "녹내장",
        "망막박리"
      ],
      "hospitals": [
        {
          "name": "무주안과의원",
          "address": "전북특별자치도 무주군 무주읍 한풍루로 351, (무주읍)",
          "tel": "063-322-6556"
        }
      ]
    },
    "치과": {
      "count": 5,
      "diseases": [
        "임플란트/치조골 이식술",
        "크라운/브릿지",
        "치주질환"
      ],
      "hospitals": [
        {
          "name": "100세 치과의원",
          "address": "전북특별자치도 무주군 안성면 안성로 288, (안성면)",
          "tel": "063-323-2875"
        },
        {
          "name": "무주연합치과의원",
          "address": "전북특별자치도 무주군 무주읍 한풍루로 351, (2층)",
          "tel": "063-322-2876"
        },
        {
          "name": "서울온정치과의원",
          "address": "전북특별자치도 무주군 무주읍 단천로 99, 1동 201호",
          "tel": "063-324-2882"
        },
        {
          "name": "우암치과의원",
          "address": "전북특별자치도 무주군 무주읍 주계로8길 6, (무주읍)",
          "tel": "063-322-3931"
        },
        {
          "name": "정치과의원",
          "address": "전북특별자치도 무주군 무주읍 당산강변로 208, (무주읍)",
          "tel": "063-322-1922"
        }
      ]
    },
    "한방내과": {
      "count": 7,
      "diseases": [
        "교통사고 첩약 처방",
        "추나요법",
        "침구 치료"
      ],
      "hospitals": [
        {
          "name": "구천동한의원",
          "address": "전북특별자치도 무주군 무주읍 주계로8길 4, 4",
          "tel": "063-322-0459"
        },
        {
          "name": "덕유산한의원",
          "address": "전북특별자치도 무주군 안성면 안성로 281, (안성면)",
          "tel": "063-323-7575"
        },
        {
          "name": "류창렬한의원",
          "address": "전북특별자치도 무주군 무주읍 주계로 73-1, (무주읍)",
          "tel": "063-322-0704"
        },
        {
          "name": "무주한의원",
          "address": "전북특별자치도 무주군 무주읍 향학로 29, 2층",
          "tel": "063-322-0644"
        },
        {
          "name": "민속한의원",
          "address": "전북특별자치도 무주군 무주읍 삼방로 756-32, (무주읍)",
          "tel": "063-322-0113"
        },
        {
          "name": "설천한의원",
          "address": "전북특별자치도 무주군 설천면 무설로 1577, (설천면)",
          "tel": "063-322-7975"
        },
        {
          "name": "정한의원",
          "address": "전북특별자치도 무주군 무주읍 당산강변로 208, 1층 정한의원",
          "tel": "063-324-5124"
        }
      ]
    }
  }
}