{
  "sido": "전남",
  "district": "진도군",
  "specialties": {
    "내과": {
      "count": 16,
      "diseases": [
        "급성 심근경색증",
        "협심증",
        "기왕증 기여도 산정",
        "고혈압성 심질환"
      ],
      "hospitals": [
        {
          "name": "의료법인남우의료재단 진도전남병원",
          "address": "전라남도 진도군 진도읍 남문길 12-11, 진도전남병원",
          "tel": "061-544-7933"
        },
        {
          "name": "진도한국병원",
          "address": "전라남도 진도군 진도읍 남문길 48, (진도읍)",
          "tel": "061-542-7575"
        },
        {
          "name": "길정신건강의학과의원",
          "address": "전라남도 진도군 진도읍 남산로 138, 1동 2층",
          "tel": "061-542-9111"
        },
        {
          "name": "김기중내과의원",
          "address": "전라남도 진도군 진도읍 남문길 13, (진도읍)",
          "tel": "061-544-8275"
        },
        {
          "name": "김흉부외과의원",
          "address": "전라남도 진도군 진도읍 남동1길 32, (진도읍)",
          "tel": "061-542-6877-8"
        },
        {
          "name": "더효사랑의원",
          "address": "전라남도 진도군 임회면 십일시길 52, (임회면)",
          "tel": "061-544-1011"
        },
        {
          "name": "서울의원",
          "address": "전라남도 진도군 고군면 오일시2길 107-9, 107",
          "tel": "061-543-7582"
        },
        {
          "name": "성심의원",
          "address": "전라남도 진도군 진도읍 남문길 27, (진도읍)",
          "tel": "061-542-7522"
        },
        {
          "name": "세종의원",
          "address": "전라남도 진도군 의신면 돈지2길 7, 세종의원",
          "tel": "061-543-7810"
        },
        {
          "name": "속편한 정내과의원",
          "address": "전라남도 진도군 진도읍 남문길 5, 진도공용버스터미널 6동 2층",
          "tel": "061-543-8575"
        },
        {
          "name": "연합의원",
          "address": "전라남도 진도군 임회면 십일시길 34, 1동 1층",
          "tel": "061-544-7553"
        },
        {
          "name": "제일의원",
          "address": "전라남도 진도군 진도읍 교동5길 11, (진도읍)",
          "tel": "061-544-2204"
        },
        {
          "name": "중앙의원",
          "address": "전라남도 진도군 진도읍 남문길 40, 중앙의원",
          "tel": "061-544-2123"
        },
        {
          "name": "진도경희의원",
          "address": "전라남도 진도군 진도읍 남문길 5, (진도읍)",
          "tel": "061-544-8987"
        },
        {
          "name": "진도의원",
          "address": "전라남도 진도군 진도읍 남문길 12-1, (진도읍)",
          "tel": "061-543-9074"
        },
        {
          "name": "현대의원",
          "address": "전라남도 진도군 지산면 지산로 1184, 1184",
          "tel": "061-542-7577"
        }
      ]
    },
    "정형외과": {
      "count": 1,
      "diseases": [
        "척추압박골절",
        "회전근개 파열",
        "십자인대 파열",
        "아킬레스건 파열",
        "반월상 연골판 파열",
        "손목/발목 골절",
        "고관절 골절"
      ],
      "hospitals": [
        {
          "name": "섬등포 팔팔정형외과의원",
          "address": "전라남도 진도군 조도면 창유1길 25, 섬등포 팔팔정형외과의원",
          "tel": "061-543-7533"
        }
      ]
    },
    "안과": {
      "count": 1,
      "diseases": [
        "백내장(다초점 렌즈)",
        "황반변성",
        "녹내장",
        "망막박리"
      ],
      "hospitals": [
        {
          "name": "이안과의원",
          "address": "전라남도 진도군 진도읍 남문길 13, 13",
          "tel": "061-542-7075"
        }
      ]
    },
    "치과": {
      "count": 6,
      "diseases": [
        "임플란트/치조골 이식술",
        "크라운/브릿지",
        "치주질환"
      ],
      "hospitals": [
        {
          "name": "뉴욕치과의원",
          "address": "전라남도 진도군 진도읍 남문길 42, 1층",
          "tel": "061-544-2827"
        },
        {
          "name": "미소치과의원",
          "address": "전라남도 진도군 진도읍 남동1길 53, (진도읍)",
          "tel": "542-2877"
        },
        {
          "name": "부부치과의원",
          "address": "전라남도 진도군 진도읍 남문길 4, (진도읍)",
          "tel": "061-542-2875"
        },
        {
          "name": "수치과의원",
          "address": "전라남도 진도군 진도읍 남문길 13, 3층",
          "tel": "061-544-7528"
        },
        {
          "name": "신치과의원",
          "address": "전라남도 진도군 진도읍 남문길 5, (진도읍)",
          "tel": "061-542-2804"
        },
        {
          "name": "한국치과의원",
          "address": "전라남도 진도군 진도읍 남문길 48, 48",
          "tel": "061-544-2828"
        }
      ]
    },
    "한방내과": {
      "count": 5,
      "diseases": [
        "교통사고 첩약 처방",
        "추나요법",
        "침구 치료"
      ],
      "hospitals": [
        {
          "name": "경희터미널한의원",
          "address": "전라남도 진도군 진도읍 남문길 5, (터미널내)",
          "tel": "061-544-1275"
        },
        {
          "name": "김명수한의원",
          "address": "전라남도 진도군 진도읍 남문길 39-4, 1층",
          "tel": "061-544-4466"
        },
        {
          "name": "동양한의원",
          "address": "전라남도 진도군 진도읍 남문길 11, (진도읍)",
          "tel": "061-542-0075"
        },
        {
          "name": "미래한의원",
          "address": "전라남도 진도군 진도읍 남문길 35, (진도읍)",
          "tel": "061-542-1075"
        },
        {
          "name": "사랑애한의원",
          "address": "전라남도 진도군 진도읍 진도대로 7143-4, (진도읍)",
          "tel": "061-544-2765"
        }
      ]
    }
  }
}