{
  "sido": "충북",
  "district": "제천시",
  "specialties": {
    "내과": {
      "count": 47,
      "diseases": [
        "급성 심근경색증",
        "협심증",
        "기왕증 기여도 산정",
        "고혈압성 심질환"
      ],
      "hospitals": [
        {
          "name": "의료법인 명지의료재단 명지병원",
          "address": "충청북도 제천시 내토로 991-0, 의료법인명지의료재단명지병원",
          "tel": "043-640-8114"
        },
        {
          "name": "의료법인 자산의료재단 제천서울병원",
          "address": "충청북도 제천시 숭문로 57-0, 서울병원",
          "tel": "043-640-7600"
        },
        {
          "name": "의료법인성지의료재단제천성지병원",
          "address": "충청북도 제천시 의림대로 284,  (청전동)",
          "tel": "043-640-3814"
        },
        {
          "name": "강남의원",
          "address": "충청북도 제천시 의병대로 88, (중앙로1가)",
          "tel": "043-653-1214"
        },
        {
          "name": "강신구내과의원",
          "address": "충청북도 제천시 의림대로 128, (중앙로1가)",
          "tel": "043-646-5858"
        },
        {
          "name": "고려의원",
          "address": "충청북도 제천시 청전대로 177, (청전동)",
          "tel": "043-652-0652"
        },
        {
          "name": "김동준소아청소년과의원",
          "address": "충청북도 제천시 용두천로 98, 2층 203호 (남천동)",
          "tel": "043-644-6080"
        },
        {
          "name": "노병연내과의원",
          "address": "충청북도 제천시 의림대로 153, 3층 (의림동)",
          "tel": "043-644-6670"
        },
        {
          "name": "뉴본의원",
          "address": "충청북도 제천시 풍양로13길 14, 4층 (중앙로2가)",
          "tel": "043-653-7080"
        },
        {
          "name": "더올린의원",
          "address": "충청북도 제천시 용두천로 117, 5층 (중앙로1가)",
          "tel": "043-756-7545"
        },
        {
          "name": "덕산연세의원",
          "address": "충청북도 제천시 덕산면 약초로 83, (덕산면)",
          "tel": "043-643-6490"
        },
        {
          "name": "명동메디칼의원",
          "address": "충청북도 제천시 용두천로 51, (명동)",
          "tel": "043-648-8275"
        },
        {
          "name": "박내과의원",
          "address": "충청북도 제천시 명륜로 97, (의림동)",
          "tel": "043-644-9465"
        },
        {
          "name": "박철민내과의원",
          "address": "충청북도 제천시 용두천로 86-1, (2층)동 (남천동)",
          "tel": "043-643-7710"
        },
        {
          "name": "백운의원",
          "address": "충청북도 제천시 백운면 평동로2길 7-11, (백운면)",
          "tel": "043-652-6160"
        },
        {
          "name": "사랑의원",
          "address": "충청북도 제천시 하소로 68, (하소동)",
          "tel": "043-642-4050"
        },
        {
          "name": "삼성의원",
          "address": "충청북도 제천시 청풍호로 100, 2층 (강제동)",
          "tel": "043-646-5578"
        },
        {
          "name": "서울소아청소년과의원",
          "address": "충청북도 제천시 풍양로 99, (중앙로1가, 주상복합건물)",
          "tel": "043-647-0522"
        },
        {
          "name": "서울연합내과의원",
          "address": "충청북도 제천시 청전대로 182, 비둘기아파트 (청전동)",
          "tel": "043-651-9100"
        },
        {
          "name": "세브란스외과의원",
          "address": "충청북도 제천시 의림대로18길 3, (중앙로2가)",
          "tel": "043-647-7717"
        },
        {
          "name": "스마트혜인의원",
          "address": "충청북도 제천시 내토로59길 31, (장락동, 신안실크밸리아파트 상가동 4층)",
          "tel": "043-652-7272"
        },
        {
          "name": "신내과의원",
          "address": "충청북도 제천시 풍양로 120, (남천동)",
          "tel": "043-643-1104"
        },
        {
          "name": "신백현대의원",
          "address": "충청북도 제천시 의병대로 238, (신백동)",
          "tel": "043-646-7582"
        },
        {
          "name": "신화의원",
          "address": "충청북도 제천시 명륜로 71, (의림동)",
          "tel": "043-643-5373"
        },
        {
          "name": "양의원",
          "address": "충청북도 제천시 풍양로 120, (남천동)",
          "tel": "043-644-5566"
        },
        {
          "name": "연세성심내과의원",
          "address": "충청북도 제천시 의림대로 222, (청전동)",
          "tel": "043-642-4539"
        },
        {
          "name": "연세의원",
          "address": "충청북도 제천시 의병대로 225, (신백동)",
          "tel": "043-652-2666"
        },
        {
          "name": "예뻐지는현의원",
          "address": "충청북도 제천시 장락로 112, 201호 (장락동)",
          "tel": "043-645-4500"
        },
        {
          "name": "원제의료소비자생활협동조합우리의원",
          "address": "충청북도 제천시 의림대로 90-1, 1,3층 (중앙로1가)",
          "tel": "043-644-1191"
        },
        {
          "name": "이록윤내과의원",
          "address": "충청북도 제천시 독순로 79, (중앙로2가)",
          "tel": "043-652-7575"
        },
        {
          "name": "이원재내과의원",
          "address": "충청북도 제천시 용두천로 117, 제천메디컬센터 4층 (중앙로1가)",
          "tel": "043-648-7553"
        },
        {
          "name": "인정신과의원",
          "address": "충청북도 제천시 의림대로 128, 우리메디컬센터빌딩3층동 (중앙로2가)",
          "tel": "043-645-7455"
        },
        {
          "name": "재림메디칼의원",
          "address": "충청북도 제천시 청전대로 216, 2,4,6,7층 (장락동)",
          "tel": "043-647-1000"
        },
        {
          "name": "정다운내과의원",
          "address": "충청북도 제천시 의림대로 222, 두손메디칼센타 3층 (청전동)",
          "tel": "043-653-7722"
        },
        {
          "name": "제천밝은미래영상의학과의원",
          "address": "충청북도 제천시 용두천로 86, 2층 (남천동)",
          "tel": "043-647-0073"
        },
        {
          "name": "제천영상의학과의원",
          "address": "충청북도 제천시 명륜로 106, (중앙로2가)",
          "tel": "043-642-4593"
        },
        {
          "name": "조성우내과의원",
          "address": "충청북도 제천시 의림대로14길 14, (중앙로1가)",
          "tel": "043-645-8581"
        },
        {
          "name": "중앙성심의원",
          "address": "충청북도 제천시 풍양로 109, (중앙로1가)",
          "tel": "043-647-0750"
        },
        {
          "name": "참조은내과의원",
          "address": "충청북도 제천시 용두천로 98, (남천동)",
          "tel": "043-646-7579"
        },
        {
          "name": "최상현내과의원",
          "address": "충청북도 제천시 용두대로15길 4, 용두시티 2층 201호 (하소동)",
          "tel": "043-647-1111"
        },
        {
          "name": "튼튼소아청소년과의원",
          "address": "충청북도 제천시 독순로 79, (중앙로2가)",
          "tel": "043-647-8500"
        },
        {
          "name": "푸른소아청소년과의원",
          "address": "충청북도 제천시 용두대로15길 4, 용두시티 2층 202호 (하소동)",
          "tel": "043-651-1500"
        },
        {
          "name": "푸른의원",
          "address": "충청북도 제천시 하소로 48, (하소동)",
          "tel": "043-647-7701"
        },
        {
          "name": "하나정신건강의학과의원",
          "address": "충청북도 제천시 풍양로 120, 4-5층 (남천동)",
          "tel": "043-652-3370"
        },
        {
          "name": "학교법인대원교육재단세명의원",
          "address": "충청북도 제천시 세명로 66, (모산동)",
          "tel": "043-649-1850"
        },
        {
          "name": "한빛의원",
          "address": "충청북도 제천시 하소로 64, (하소동)",
          "tel": "043-645-2676"
        },
        {
          "name": "한사랑외과의원",
          "address": "충청북도 제천시 풍양로 107, (중앙로1가)",
          "tel": "043-644-3800"
        }
      ]
    },
    "신경외과": {
      "count": 2,
      "diseases": [
        "목/허리디스크(추간판탈출증)",
        "척추관협착증",
        "외상성 뇌출혈",
        "경추/요추 염좌",
        "뇌경색"
      ],
      "hospitals": [
        {
          "name": "강중식신경외과의원",
          "address": "충청북도 제천시 의림대로 153, 2,4,5층 (의림동)",
          "tel": "043-642-0050"
        },
        {
          "name": "위성목신경외과의원",
          "address": "충청북도 제천시 의림대로 122, (중앙로2가)",
          "tel": "043-648-8797"
        }
      ]
    },
    "정형외과": {
      "count": 9,
      "diseases": [
        "척추압박골절",
        "회전근개 파열",
        "십자인대 파열",
        "아킬레스건 파열",
        "반월상 연골판 파열",
        "손목/발목 골절",
        "고관절 골절"
      ],
      "hospitals": [
        {
          "name": "굿모닝정형외과의원",
          "address": "충청북도 제천시 의병대로 107, (남천동)",
          "tel": "043-648-5111"
        },
        {
          "name": "기운찬정형외과의원",
          "address": "충청북도 제천시 독순로 79, 내토메디컬센터 201호 (중앙로2가)",
          "tel": "043-642-0001"
        },
        {
          "name": "노정형외과의원",
          "address": "충청북도 제천시 의림대로 222, (청전동, 두손메디칼센타)",
          "tel": "043-652-5000"
        },
        {
          "name": "삼성바른정형외과의원",
          "address": "충청북도 제천시 의림대로 123, 2층 (중앙로2가)",
          "tel": "043-643-3300"
        },
        {
          "name": "서울정형외과의원",
          "address": "충청북도 제천시 용두천로 117, 2층 (중앙로1가)",
          "tel": "043-646-4300"
        },
        {
          "name": "연세푸른정형외과의원",
          "address": "충청북도 제천시 용두천로 98, (남천동)",
          "tel": "043-653-7575"
        },
        {
          "name": "제일정형외과의원",
          "address": "충청북도 제천시 명륜로 81, 예건빌딩 (의림동)",
          "tel": "043-642-8855"
        },
        {
          "name": "킴스정형외과의원",
          "address": "충청북도 제천시 의림대로 139, (중앙로2가)",
          "tel": "043-652-0113"
        },
        {
          "name": "한솔정형외과의원",
          "address": "충청북도 제천시 의병대로 113, (남천동)",
          "tel": "043-646-4177"
        }
      ]
    },
    "산부인과": {
      "count": 7,
      "diseases": [
        "자궁근종(하이푸 시술)",
        "유방 섬유선종(맘모톰)",
        "요실금 수술",
        "자궁경부암"
      ],
      "hospitals": [
        {
          "name": "김태웅산부인과의원",
          "address": "충청북도 제천시 명륜로 79, (의림동)",
          "tel": "043-652-0815"
        },
        {
          "name": "모아산부인과의원",
          "address": "충청북도 제천시 명륜로 91, (의림동)",
          "tel": "043-645-6601"
        },
        {
          "name": "미래산부인과의원",
          "address": "충청북도 제천시 용두대로15길 4, 3층 (하소동)",
          "tel": "043-645-6336"
        },
        {
          "name": "엄기명산부인과의원",
          "address": "충청북도 제천시 독순로 64, (중앙로2가)",
          "tel": "043-644-6366"
        },
        {
          "name": "엄승호산부인과의원",
          "address": "충청북도 제천시 동명로 58, (명동)",
          "tel": "043-647-1411"
        },
        {
          "name": "연세미즈산부인과의원",
          "address": "충청북도 제천시 독순로 79, (중앙로2가, 내토메디컬센터)",
          "tel": "043-652-6700"
        },
        {
          "name": "한기정산부인과의원",
          "address": "충청북도 제천시 의병대로 82, (중앙로1가)",
          "tel": "043-645-0091"
        }
      ]
    },
    "피부과": {
      "count": 2,
      "diseases": [
        "여드름/레이저 미용",
        "흉터 레이저(핀홀 시술)",
        "대상포진"
      ],
      "hospitals": [
        {
          "name": "맑은피부과의원",
          "address": "충청북도 제천시 의림대로 222, (청전동)",
          "tel": "043-643-5900"
        },
        {
          "name": "연세피부과의원",
          "address": "충청북도 제천시 독순로 79, (중앙로2가)",
          "tel": "043-644-4045"
        }
      ]
    },
    "가정의학과": {
      "count": 1,
      "diseases": [
        "만성질환 관리",
        "건강검진",
        "비만 치료"
      ],
      "hospitals": [
        {
          "name": "박가정의학과의원",
          "address": "충청북도 제천시 용두천로 78, 2층 (남천동)",
          "tel": "043-647-7000"
        }
      ]
    },
    "재활의학과": {
      "count": 1,
      "diseases": [
        "도수치료",
        "체외충격파치료(ESWT)",
        "통증 재활"
      ],
      "hospitals": [
        {
          "name": "박용수재활의학과의원",
          "address": "충청북도 제천시 의병대로 105, (남천동)",
          "tel": "043-644-1119"
        }
      ]
    },
    "이비인후과": {
      "count": 5,
      "diseases": [
        "후두염",
        "만성 부비동염",
        "이명/난청",
        "편도선 수술"
      ],
      "hospitals": [
        {
          "name": "베스트성모이비인후과의원",
          "address": "충청북도 제천시 의림대로 178, (중앙로2가)",
          "tel": "043-643-2366"
        },
        {
          "name": "서울이비인후과의원",
          "address": "충청북도 제천시 용두천로 117, 3층 (중앙로1가)",
          "tel": "043-647-0529"
        },
        {
          "name": "최이비인후과의원",
          "address": "충청북도 제천시 의림대로 85, (명동)",
          "tel": "043-644-4475"
        },
        {
          "name": "코코이비인후과의원",
          "address": "충청북도 제천시 독순로 79, (중앙로2가)",
          "tel": "043-642-2277"
        },
        {
          "name": "필이비인후과의원",
          "address": "충청북도 제천시 용두천로 98, (남천동)",
          "tel": "043-643-7570"
        }
      ]
    },
    "마취통증의학과": {
      "count": 2,
      "diseases": [
        "신경차단술",
        "경막외 스테로이드",
        "관절강 내 주사"
      ],
      "hospitals": [
        {
          "name": "삼성마취통증의원",
          "address": "충청북도 제천시 풍양로13길 5, (중앙로1가)",
          "tel": "043-646-7575"
        },
        {
          "name": "연세올바른마취통증의학과의원",
          "address": "충청북도 제천시 용두천로 88, 영창빌딩 4층 (남천동)",
          "tel": "043-644-7582"
        }
      ]
    },
    "비뇨의학과": {
      "count": 2,
      "diseases": [
        "전립선비대증(유로리프트)",
        "요로결석 쇄석술",
        "방광암"
      ],
      "hospitals": [
        {
          "name": "성모비뇨기과의원",
          "address": "충청북도 제천시 용두천로 98, (남천동)",
          "tel": "043-648-5571"
        },
        {
          "name": "이비뇨기과의원",
          "address": "충청북도 제천시 풍양로13길 12, (중앙로1가)",
          "tel": "043-646-9406"
        }
      ]
    },
    "안과": {
      "count": 5,
      "diseases": [
        "백내장(다초점 렌즈)",
        "황반변성",
        "녹내장",
        "망막박리"
      ],
      "hospitals": [
        {
          "name": "연세안과의원",
          "address": "충청북도 제천시 의림대로 128, (중앙로2가)",
          "tel": "043-643-3355"
        },
        {
          "name": "연세프라임안과의원",
          "address": "충청북도 제천시 용두천로 98, 2층 (남천동)",
          "tel": "043-646-3333"
        },
        {
          "name": "온빛안과의원",
          "address": "충청북도 제천시 용두천로 88, 영창빌딩 2,3층 (남천동)",
          "tel": "043-756-7577"
        },
        {
          "name": "이진영안과의원",
          "address": "충청북도 제천시 의림대로 180, (중앙로2가)",
          "tel": "043-645-3900"
        },
        {
          "name": "제천밝은안과의원",
          "address": "충청북도 제천시 의림대로 222, (청전동, 두손메디칼센타)",
          "tel": "043-643-4200"
        }
      ]
    },
    "신경과": {
      "count": 1,
      "diseases": [
        "뇌졸중(뇌경색/뇌출혈)",
        "파킨슨병",
        "편두통"
      ],
      "hospitals": [
        {
          "name": "황민호신경과의원",
          "address": "충청북도 제천시 의림대로 222, 두손메디칼센타 6층 (청전동)",
          "tel": "043-653-7118"
        }
      ]
    },
    "치과": {
      "count": 45,
      "diseases": [
        "임플란트/치조골 이식술",
        "크라운/브릿지",
        "치주질환"
      ],
      "hospitals": [
        {
          "name": "건치과의원",
          "address": "충청북도 제천시 용두천로 98, (남천동)",
          "tel": "043-647-2275"
        },
        {
          "name": "두리연치과의원",
          "address": "충청북도 제천시 용두천로 88, (남천동, 영창빌딩)",
          "tel": "043-716-2879"
        },
        {
          "name": "두손치과의원",
          "address": "충청북도 제천시 의림대로 222, (청전동)",
          "tel": "043-643-0220"
        },
        {
          "name": "라온치과의원",
          "address": "충청북도 제천시 의림대로31길 3, (청전동)",
          "tel": "043-724-0007"
        },
        {
          "name": "로이스치과의원",
          "address": "충청북도 제천시 의림대로 212, 옥란빌딩 5층 (청전동)",
          "tel": "043-648-2828"
        },
        {
          "name": "명성웰치과의원",
          "address": "충청북도 제천시 풍양로13길 14, (중앙로2가)",
          "tel": "043-645-2815"
        },
        {
          "name": "미래치과의원",
          "address": "충청북도 제천시 의림대로 136, (중앙로2가)",
          "tel": "043-648-0570"
        },
        {
          "name": "바른치과의원",
          "address": "충청북도 제천시 의림대로 123, (중앙로2가)",
          "tel": "043-643-2727"
        },
        {
          "name": "베스트치과의원",
          "address": "충청북도 제천시 용두천로 117, 5층 502호 (중앙로1가)",
          "tel": "043-724-2228"
        },
        {
          "name": "봉양미소치과의원",
          "address": "충청북도 제천시 봉양읍 주포로5길 2, (봉양읍)",
          "tel": "043-642-2870"
        },
        {
          "name": "부부치과의원",
          "address": "충청북도 제천시 독순로 74, (중앙로2가)",
          "tel": "043-645-0698"
        },
        {
          "name": "삼성제일치과의원",
          "address": "충청북도 제천시 의림대로 119, (중앙로1가)",
          "tel": "043-651-2828"
        },
        {
          "name": "상아치과의원",
          "address": "충청북도 제천시 의림대로 113-10, (중앙로1가)",
          "tel": "043-646-4567"
        },
        {
          "name": "서울강남플란트치과의원",
          "address": "충청북도 제천시 독순로 71, 2.3층 (중앙로2가)",
          "tel": "043-642-2875"
        },
        {
          "name": "서울미래치과교정과치과의원",
          "address": "충청북도 제천시 의림대로 123, 5층 (중앙로2가)",
          "tel": "043-648-2275"
        },
        {
          "name": "서울미소플란트치과의원",
          "address": "충청북도 제천시 용두천로 86, 3층 (남천동)",
          "tel": "043-651-2275"
        },
        {
          "name": "서울준치과의원",
          "address": "충청북도 제천시 장락로 146, (장락동)",
          "tel": "043-642-2275"
        },
        {
          "name": "선치과의원",
          "address": "충청북도 제천시 하소로 74, (하소동)",
          "tel": "043-652-2804"
        },
        {
          "name": "세브란스치과의원",
          "address": "충청북도 제천시 의병대로 105, 4층 (남천동)",
          "tel": "043-648-1118"
        },
        {
          "name": "스마일치과의원",
          "address": "충청북도 제천시 용두대로15길 4, 2층 203호 (하소동)",
          "tel": "043-643-2275"
        },
        {
          "name": "스타치과의원",
          "address": "충청북도 제천시 의림대로 167, 4층 (의림동)",
          "tel": "043-645-0028"
        },
        {
          "name": "엄윤섭구강악안면외과치과의원",
          "address": "충청북도 제천시 풍양로 101, 2층 (중앙로1가)",
          "tel": "043-645-0275"
        },
        {
          "name": "연세e좋은치과의원",
          "address": "충청북도 제천시 청풍호로 100, 201호 (강제동)",
          "tel": "043-648-2882"
        },
        {
          "name": "연세미시간치과의원",
          "address": "충청북도 제천시 용두천로 72, 1층 (남천동)",
          "tel": "043-647-2882"
        },
        {
          "name": "연세치과의원",
          "address": "충청북도 제천시 풍양로 103, (중앙로1가)",
          "tel": "043-643-0668"
        },
        {
          "name": "오치과의원",
          "address": "충청북도 제천시 의림대로 115, 2층 (중앙로1가)",
          "tel": "043-644-2275"
        },
        {
          "name": "올치과의원",
          "address": "충청북도 제천시 의림대로 128, (중앙로2가)",
          "tel": "043-653-2275"
        },
        {
          "name": "우리치과의원",
          "address": "충청북도 제천시 청전대로 171, (청전동)",
          "tel": "043-648-6698"
        },
        {
          "name": "원플란트치과의원",
          "address": "충청북도 제천시 의림대로14길 2, (중앙로1가)",
          "tel": "043-653-2882"
        },
        {
          "name": "유치과의원",
          "address": "충청북도 제천시 의병대로 230-1, (신백동)",
          "tel": "043-642-7582"
        },
        {
          "name": "이성우치과의원",
          "address": "충청북도 제천시 명륜로 105, 2층 (중앙로2가)",
          "tel": "043-653-2875"
        },
        {
          "name": "이치과의원",
          "address": "충청북도 제천시 의병대로 89, (중앙로1가)",
          "tel": "043-647-2875"
        },
        {
          "name": "이편한치과의원",
          "address": "충청북도 제천시 용두천로 382, (고암동)",
          "tel": "043-646-2050"
        },
        {
          "name": "장세혁치과의원",
          "address": "충청북도 제천시 의림대로 121, (중앙로2가)",
          "tel": "043-648-3275"
        },
        {
          "name": "채치과의원",
          "address": "충청북도 제천시 의림대로 97, (명동)",
          "tel": "043-645-0011"
        },
        {
          "name": "최유정치과의원",
          "address": "충청북도 제천시 풍양로 120, 5층 (남천동)",
          "tel": "043-920-7771"
        },
        {
          "name": "탑치과의원",
          "address": "충청북도 제천시 용두대로15길 23, 2층 (하소동)",
          "tel": "043-645-2275"
        },
        {
          "name": "터미널민치과의원",
          "address": "충청북도 제천시 명륜로 81, 301호 (의림동)",
          "tel": "043-642-2001"
        },
        {
          "name": "튼튼치과의원",
          "address": "충청북도 제천시 명륜로 97, (의림동)",
          "tel": "043-646-2875"
        },
        {
          "name": "플란트임치과의원",
          "address": "충청북도 제천시 청전대로 177, (청전동)",
          "tel": "043-643-9440"
        },
        {
          "name": "하나치과의원",
          "address": "충청북도 제천시 청전대로 216, (장락동, 재림빌딩302호)",
          "tel": "043-646-6606"
        },
        {
          "name": "한미치과의원",
          "address": "충청북도 제천시 독순로 64, (중앙로2가)",
          "tel": "043-652-2801"
        },
        {
          "name": "행복이가득한치과의원",
          "address": "충청북도 제천시 칠성로6길 2, (의림동)",
          "tel": "043-648-2804"
        },
        {
          "name": "허창재치과의원",
          "address": "충청북도 제천시 독순로 79, (중앙로2가)",
          "tel": "043-648-7575"
        },
        {
          "name": "현대치과의원",
          "address": "충청북도 제천시 하소로 64, (하소동)",
          "tel": "043-645-2875"
        }
      ]
    },
    "한방내과": {
      "count": 39,
      "diseases": [
        "교통사고 첩약 처방",
        "추나요법",
        "침구 치료"
      ],
      "hospitals": [
        {
          "name": "대원교육재단 세명대학교 부속한방병원",
          "address": "충청북도 제천시 세명로 66-0, 세명대한방병원",
          "tel": "043-645-1010"
        },
        {
          "name": "거북당한의원",
          "address": "충청북도 제천시 의림대로 136, (중앙로2가)",
          "tel": "043-646-1075"
        },
        {
          "name": "경희길한의원",
          "address": "충청북도 제천시 의림대로 145, (중앙로2가)",
          "tel": "043-647-1515"
        },
        {
          "name": "경희은생한의원",
          "address": "충청북도 제천시 의림대로 254, 1~2층 (청전동)",
          "tel": "043-645-2012"
        },
        {
          "name": "경희한의원",
          "address": "충청북도 제천시 청전대로15길 6, (청전동)",
          "tel": "043-646-0300"
        },
        {
          "name": "고려한의원",
          "address": "충청북도 제천시 덕산면 약초로3길 7, 7",
          "tel": "043-644-6836"
        },
        {
          "name": "광제한의원",
          "address": "충청북도 제천시 의림대로 183, (중앙로2가)",
          "tel": "043-642-2504"
        },
        {
          "name": "구침한의원",
          "address": "충청북도 제천시 용두대로15길 16, (하소동)",
          "tel": "043-653-1002"
        },
        {
          "name": "남창규한의원",
          "address": "충청북도 제천시 의림대로 118, (중앙로1가)",
          "tel": "043-646-8075"
        },
        {
          "name": "내토한의원",
          "address": "충청북도 제천시 용두천로11길 4, (중앙로1가)",
          "tel": "043-646-1688"
        },
        {
          "name": "대동한의원",
          "address": "충청북도 제천시 명륜로 123, (중앙로2가)",
          "tel": "043-646-8275"
        },
        {
          "name": "동방한의원",
          "address": "충청북도 제천시 내토로 440, (영천동)",
          "tel": "043-647-2332"
        },
        {
          "name": "동양한의원",
          "address": "충청북도 제천시 의림대로 141, (중앙로2가)",
          "tel": "043-652-1075"
        },
        {
          "name": "맑은샘한의원",
          "address": "충청북도 제천시 독순로 105, (남천동)",
          "tel": "043-645-3475"
        },
        {
          "name": "맥한의원",
          "address": "충청북도 제천시 용두천로 118, 3층 (남천동, 초계빌딩)",
          "tel": "043-920-8888"
        },
        {
          "name": "명문당한의원",
          "address": "충청북도 제천시 독순로 79, 내토메디컬센터 3층 302호 (중앙로2가)",
          "tel": "043-647-3375"
        },
        {
          "name": "명의촌한의원",
          "address": "충청북도 제천시 명륜로 91, 3층 (의림동)",
          "tel": "043-653-7730"
        },
        {
          "name": "명진한의원",
          "address": "충청북도 제천시 용두천로 86-1, (남천동)",
          "tel": "043-645-1075"
        },
        {
          "name": "미소랑한의원",
          "address": "충청북도 제천시 내토로 587, 1,2층 (동현동)",
          "tel": "043-643-1072"
        },
        {
          "name": "바른한의원",
          "address": "충청북도 제천시 풍양로 108, 중앙시장상가 다동 1층 22호 (중앙로1가)",
          "tel": "043-642-8585"
        },
        {
          "name": "부원당한의원",
          "address": "충청북도 제천시 의림대로 150-1, (중앙로2가)",
          "tel": "043-644-8575"
        },
        {
          "name": "생기한의원",
          "address": "충청북도 제천시 용두천로 388, (고암동)",
          "tel": "043-920-1020"
        },
        {
          "name": "서울한의원",
          "address": "충청북도 제천시 의림대로 252, (청전동)",
          "tel": "043-643-0335"
        },
        {
          "name": "성문한의원",
          "address": "충청북도 제천시 의림대로14길 11, 1층 (중앙로2가)",
          "tel": "043-645-7586"
        },
        {
          "name": "송수한의원",
          "address": "충청북도 제천시 독순로 81, (중앙로2가, (2층))",
          "tel": "043-646-6688"
        },
        {
          "name": "수창한의원",
          "address": "충청북도 제천시 용두천로 107, (중앙로1가)",
          "tel": "043-651-0030"
        },
        {
          "name": "쉼한의원",
          "address": "충청북도 제천시 청풍면 비봉2길 99-39, 1,2층",
          "tel": "043-644-1075"
        },
        {
          "name": "신농씨한의원",
          "address": "충청북도 제천시 용두천로 110, (남천동)",
          "tel": "043-648-3375"
        },
        {
          "name": "신한한의원",
          "address": "충청북도 제천시 독순로 71, (중앙로2가)",
          "tel": "043-646-2778"
        },
        {
          "name": "안심부부한의원",
          "address": "충청북도 제천시 의림대로 222, 두손메디칼센타 5층 (청전동)",
          "tel": "043-647-1075"
        },
        {
          "name": "약손한의원",
          "address": "충청북도 제천시 풍양로 122, (남천동)",
          "tel": "043-652-8075"
        },
        {
          "name": "연세의원참사랑한의원",
          "address": "충청북도 제천시 의병대로 225, (신백동)",
          "tel": "043-652-2666"
        },
        {
          "name": "외갓집한의원",
          "address": "충청북도 제천시 용두천로 94, 1~2층 (남천동)",
          "tel": "043-756-8875"
        },
        {
          "name": "인성한의원",
          "address": "충청북도 제천시 의림대로16길 19, (중앙로2가)",
          "tel": "043-646-1060"
        },
        {
          "name": "자연한의원",
          "address": "충청북도 제천시 풍양로13길 14, (중앙로2가)",
          "tel": "043-644-2582"
        },
        {
          "name": "제일한의원",
          "address": "충청북도 제천시 의림대로 144, (중앙로2가)",
          "tel": "043-645-0555"
        },
        {
          "name": "중화당한의원",
          "address": "충청북도 제천시 독순로 64, 1층 (중앙로2가)",
          "tel": "043-647-5306"
        },
        {
          "name": "품한의원",
          "address": "충청북도 제천시 내토로59길 31, (장락동, 신안실크밸리아파트 상가동)",
          "tel": "043-645-7577"
        },
        {
          "name": "혜민서한의원",
          "address": "충청북도 제천시 용두대로15다길 6, (하소동)",
          "tel": "043-653-1291"
        }
      ]
    }
  }
}